parselib/__init__.py
parselib/element.py
parselib/finder.py
parselib/parser.py
parselib-0.0.5.dist-info/METADATA
parselib-0.0.5.dist-info/WHEEL
parselib-0.0.5.dist-info/licenses/LICENSE
parselib-0.0.5.dist-info/RECORD
