Metadata-Version: 2.1
Name: parselib
Version: 0.0.5
Summary: HTML parser for web scraping
Project-URL: Homepage, https://github.com/chemtrails/parselib
Author: Rafał Prażmo
License-File: LICENSE
Classifier: License :: OSI Approved :: MIT License
Classifier: Operating System :: OS Independent
Classifier: Programming Language :: Python :: 3
Requires-Python: >=3.7
